Topsis_102003448/__init__.py
Topsis_102003448/topsis_102003448.py
Topsis_102003448-0.1.dist-info/LICENSE.txt
Topsis_102003448-0.1.dist-info/METADATA
Topsis_102003448-0.1.dist-info/WHEEL
Topsis_102003448-0.1.dist-info/top_level.txt
Topsis_102003448-0.1.dist-info/RECORD
